urler/__init__.py
urler/urler.py
urler-0.1.1.dist-info/DESCRIPTION.rst
urler-0.1.1.dist-info/METADATA
urler-0.1.1.dist-info/RECORD
urler-0.1.1.dist-info/WHEEL
urler-0.1.1.dist-info/entry_points.txt
urler-0.1.1.dist-info/metadata.json
urler-0.1.1.dist-info/top_level.txt
