Metadata-Version: 2.0
Name: urler
Version: 0.1.1
Summary: URLer - GET it?
Home-page: https://github.com/kintoandar/urler
Author: Joel Bastos
Author-email: kintoandar@gmail.com
License: MIT
Keywords: urler
Platform: UNKNOWN
Classifier: Development Status :: 2 - Pre-Alpha
Classifier: Intended Audience :: System Administrators
Classifier: License :: OSI Approved :: MIT License
Classifier: Natural Language :: English
Classifier: Programming Language :: Python :: 2
Classifier: Programming Language :: Python :: 2.6
Classifier: Programming Language :: Python :: 2.7
Classifier: Programming Language :: Python :: 3
Classifier: Programming Language :: Python :: 3.3
Classifier: Programming Language :: Python :: 3.4
Classifier: Programming Language :: Python :: 3.5
Requires-Dist: docopt (>=0.6.2)
Requires-Dist: urllib3 (>=1.9.1)
Requires-Dist: wsgiref (>=0.1.2)
